minos/plugins/aiopg/__init__.py
minos/plugins/aiopg/clients.py
minos/plugins/aiopg/factories/__init__.py
minos/plugins/aiopg/factories/aggregate/__init__.py
minos/plugins/aiopg/factories/aggregate/events.py
minos/plugins/aiopg/factories/aggregate/snapshots/__init__.py
minos/plugins/aiopg/factories/aggregate/snapshots/impl.py
minos/plugins/aiopg/factories/aggregate/snapshots/queries.py
minos/plugins/aiopg/factories/aggregate/transactions.py
minos/plugins/aiopg/factories/common/__init__.py
minos/plugins/aiopg/factories/common/locks.py
minos/plugins/aiopg/factories/common/managemens.py
minos/plugins/aiopg/factories/networks/__init__.py
minos/plugins/aiopg/factories/networks/collections/__init__.py
minos/plugins/aiopg/factories/networks/collections/queues.py
minos/plugins/aiopg/factories/networks/publishers/__init__.py
minos/plugins/aiopg/factories/networks/publishers/queues.py
minos/plugins/aiopg/factories/networks/subscribers/__init__.py
minos/plugins/aiopg/factories/networks/subscribers/queues.py
minos/plugins/aiopg/factories/networks/subscribers/validators.py
minos/plugins/aiopg/operations.py
minos_database_aiopg-0.7.0.dist-info/LICENSE
minos_database_aiopg-0.7.0.dist-info/WHEEL
minos_database_aiopg-0.7.0.dist-info/METADATA
minos_database_aiopg-0.7.0.dist-info/RECORD
